Workbook

Sheet Transactions
A1: Date | B1: Description | C1: Category | D1: Account | E1: Amount | F1: Month | G1: Type
A2: 45699 | B2: Side Hustle txn | C2: Side Hustle | D2: Checking | E2: 1244.99 | F2: Feb | G2: Income
A3: 45664 | B3: Share Dividends txn | C3: Share Dividends | D3: Checking | E3: 2481.7 | F3: Jan | G3: Income
A4: 45670 | B4: Discretionary Spending txn | C4: Discretionary Spending | D4: Checking | E4: -1169.75 | F4: Jan | G4: Expense
A5: 45722 | B5: Savings txn | C5: Savings | D5: Checking | E5: -84.62 | F5: Mar | G5: Savings
A6: 45713 | B6: Health txn | C6: Health | D6: Checking | E6: -149.01 | F6: Feb | G6: Expense
A7: 45669 | B7: Health txn | C7: Health | D7: Checking | E7: -127.63 | F7: Jan | G7: Expense
A8: 45730 | B8: eBay txn | C8: eBay | D8: Checking | E8: 2847.6 | F8: Mar | G8: Income
A9: 45738 | B9: Interest - Bank Accounts txn | C9: Interest - Bank Accounts | D9: Checking | E9: 1773.6 | F9: Mar | G9: Income
A10: 45708 | B10: Interest - Bank Accounts txn | C10: Interest - Bank Accounts | D10: Checking | E10: 2931.14 | F10: Feb | G10: Income
A11: 45663 | B11: Side Hustle txn | C11: Side Hustle | D11: Checking | E11: 939.87 | F11: Jan | G11: Income
A12: 45676 | B12: eBay txn | C12: eBay | D12: Checking | E12: 1755.65 | F12: Jan | G12: Income
A13: 45729 | B13: Partner Income txn | C13: Partner Income | D13: Checking | E13: 398.86 | F13: Mar | G13: Income
... A121: 45713 | B121: Travel txn | C121: Travel | D121: Checking | E121: -813.58 | F121: Feb | G121: Expense

Sheet Year Detail
A1: INCOME & EXPENSES
B2: Jan | C2: Feb | D2: Mar | E2: Apr | F2: May | G2: Jun | H2: Jul | I2: Aug | J2: Sep | K2: Oct | L2: Nov | M2: Dec | N2: TOTAL
A3: INCOME 1
A4: Main Income Source | B4: =SUMIFS(Transactions!$E:$E,Transactions!$C:$C,$A4,Transactions!$F:$F,"Jan") -> 679.64 | C4: =SUMIFS(Transactions!$E:$E,Transactions!$C:$C,$A4,Transactions!$F:$F,"Feb") -> 303.92 | D4: =SUMIFS(Transactions!$E:$E,Transactions!$C:$C,$A4,Transactions!$F:$F,"Mar") -> 6093.06 | E4: =SUMIFS(Transactions!$E:$E,Transactions!$C:$C,$A4,Transactions!$F:$F,"Apr") -> 0 | F4: =SUMIFS(Transactions!$E:$E,Transactions!$C:$C,$A4,Transactions!$F:$F,"May") -> 0 | G4: =SUMIFS(Transactions!$E:$E,Transactions!$C:$C,$A4,Transactions!$F:$F,"Jun") -> 0 | H4: =SUMIFS(Transactions!$E:$E,Transactions!$C:$C,$A4,Transactions!$F:$F,"Jul") -> 0 | I4: =SUMIFS(Transactions!$E:$E,Transactions!$C:$C,$A4,Transactions!$F:$F,"Aug") -> 0 | J4: =SUMIFS(Transactions!$E:$E,Transactions!$C:$C,$A4,Transactions!$F:$F,"Sep") -> 0 | K4: =SUMIFS(Transactions!$E:$E,Transactions!$C:$C,$A4,Transactions!$F:$F,"Oct") -> 0 | L4: =SUMIFS(Transactions!$E:$E,Transactions!$C:$C,$A4,Transactions!$F:$F,"Nov") -> 0 | M4: =SUMIFS(Transactions!$E:$E,Transactions!$C:$C,$A4,Transactions!$F:$F,"Dec") -> 0 | N4: =SUM(B4:M4) -> 7076.62
A5: Interest - Bank Accounts | B5: =SUMIFS(Transactions!$E:$E,Transactions!$C:$C,$A5,Transactions!$F:$F,"Jan") -> 2220.36 | C5: =SUMIFS(Transactions!$E:$E,Transactions!$C:$C,$A5,Transactions!$F:$F,"Feb") -> 3980.81 | D5: =SUMIFS(Transactions!$E:$E,Transactions!$C:$C,$A5,Transactions!$F:$F,"Mar") -> 3197.87 | E5: =SUMIFS(Transactions!$E:$E,Transactions!$C:$C,$A5,Transactions!$F:$F,"Apr") -> 0 | F5: =SUMIFS(Transactions!$E:$E,Transactions!$C:$C,$A5,Transactions!$F:$F,"May") -> 0 | G5: =SUMIFS(Transactions!$E:$E,Transactions!$C:$C,$A5,Transactions!$F:$F,"Jun") -> 0 | H5: =SUMIFS(Transactions!$E:$E,Transactions!$C:$C,$A5,Transactions!$F:$F,"Jul") -> 0 | I5: =SUMIFS(Transactions!$E:$E,Transactions!$C:$C,$A5,Transactions!$F:$F,"Aug") -> 0 | J5: =SUMIFS(Transactions!$E:$E,Transactions!$C:$C,$A5,Transactions!$F:$F,"Sep") -> 0 | K5: =SUMIFS(Transactions!$E:$E,Transactions!$C:$C,$A5,Transactions!$F:$F,"Oct") -> 0 | L5: =SUMIFS(Transactions!$E:$E,Transactions!$C:$C,$A5,Transactions!$F:$F,"Nov") -> 0 | M5: =SUMIFS(Transactions!$E:$E,Transactions!$C:$C,$A5,Transactions!$F:$F,"Dec") -> 0 | N5: =SUM(B5:M5) -> 9399.04
A6: Share Dividends | B6: =SUMIFS(Transactions!$E:$E,Transactions!$C:$C,$A6,Transactions!$F:$F,"Jan") -> 3092.73 | C6: =SUMIFS(Transactions!$E:$E,Transactions!$C:$C,$A6,Transactions!$F:$F,"Feb") -> 6938.65 | D6: =SUMIFS(Transactions!$E:$E,Transactions!$C:$C,$A6,Transactions!$F:$F,"Mar") -> 4636.39 | E6: =SUMIFS(Transactions!$E:$E,Transactions!$C:$C,$A6,Transactions!$F:$F,"Apr") -> 0 | F6: =SUMIFS(Transactions!$E:$E,Transactions!$C:$C,$A6,Transactions!$F:$F,"May") -> 0 | G6: =SUMIFS(Transactions!$E:$E,Transactions!$C:$C,$A6,Transactions!$F:$F,"Jun") -> 0 | H6: =SUMIFS(Transactions!$E:$E,Transactions!$C:$C,$A6,Transactions!$F:$F,"Jul") -> 0 | I6: =SUMIFS(Transactions!$E:$E,Transactions!$C:$C,$A6,Transactions!$F:$F,"Aug") -> 0 | J6: =SUMIFS(Transactions!$E:$E,Transactions!$C:$C,$A6,Transactions!$F:$F,"Sep") -> 0 | K6: =SUMIFS(Transactions!$E:$E,Transactions!$C:$C,$A6,Transactions!$F:$F,"Oct") -> 0 | L6: =SUMIFS(Transactions!$E:$E,Transactions!$C:$C,$A6,Transactions!$F:$F,"Nov") -> 0 | M6: =SUMIFS(Transactions!$E:$E,Transactions!$C:$C,$A6,Transactions!$F:$F,"Dec") -> 0 | N6: =SUM(B6:M6) -> 14667.77
A7: eBay | B7: =SUMIFS(Transactions!$E:$E,Transactions!$C:$C,$A7,Transactions!$F:$F,"Jan") -> 7650.98 | C7: =SUMIFS(Transactions!$E:$E,Transactions!$C:$C,$A7,Transactions!$F:$F,"Feb") -> 1496.42 | D7: =SUMIFS(Transactions!$E:$E,Transactions!$C:$C,$A7,Transactions!$F:$F,"Mar") -> 9284.36 | E7: =SUMIFS(Transactions!$E:$E,Transactions!$C:$C,$A7,Transactions!$F:$F,"Apr") -> 0 | F7: =SUMIFS(Transactions!$E:$E,Transactions!$C:$C,$A7,Transactions!$F:$F,"May") -> 0 | G7: =SUMIFS(Transactions!$E:$E,Transactions!$C:$C,$A7,Transactions!$F:$F,"Jun") -> 0 | H7: =SUMIFS(Transactions!$E:$E,Transactions!$C:$C,$A7,Transactions!$F:$F,"Jul") -> 0 | I7: =SUMIFS(Transactions!$E:$E,Transactions!$C:$C,$A7,Transactions!$F:$F,"Aug") -> 0 | J7: =SUMIFS(Transactions!$E:$E,Transactions!$C:$C,$A7,Transactions!$F:$F,"Sep") -> 0 | K7: =SUMIFS(Transactions!$E:$E,Transactions!$C:$C,$A7,Transactions!$F:$F,"Oct") -> 0 | L7: =SUMIFS(Transactions!$E:$E,Transactions!$C:$C,$A7,Transactions!$F:$F,"Nov") -> 0 | M7: =SUMIFS(Transactions!$E:$E,Transactions!$C:$C,$A7,Transactions!$F:$F,"Dec") -> 0 | N7: =SUM(B7:M7) -> 18431.76
A8: TOTAL INCOME 1 | B8: =SUM(B4:B7) -> 13643.71 | C8: =SUM(C4:C7) -> 12719.8 | D8: =SUM(D4:D7) -> 23211.68 | E8: =SUM(E4:E7) -> 0 | F8: =SUM(F4:F7) -> 0 | G8: =SUM(G4:G7) -> 0 | H8: =SUM(H4:H7) -> 0 | I8: =SUM(I4:I7) -> 0 | ... M8: =SUM(M4:M7) -> 0 | N8: =SUM(B8:M8) -> 49575.19
A9: INCOME 2
A10: Side Hustle | B10: =SUMIFS(Transactions!$E:$E,Transactions!$C:$C,$A10,Transactions!$F:$F,"Jan") -> 2254.81 | C10: =SUMIFS(Transactions!$E:$E,Transactions!$C:$C,$A10,Transactions!$F:$F,"Feb") -> 5453.97 | D10: =SUMIFS(Transactions!$E:$E,Transactions!$C:$C,$A10,Transactions!$F:$F,"Mar") -> 5172.04 | E10: =SUMIFS(Transactions!$E:$E,Transactions!$C:$C,$A10,Transactions!$F:$F,"Apr") -> 0 | F10: =SUMIFS(Transactions!$E:$E,Transactions!$C:$C,$A10,Transactions!$F:$F,"May") -> 0 | G10: =SUMIFS(Transactions!$E:$E,Transactions!$C:$C,$A10,Transactions!$F:$F,"Jun") -> 0 | H10: =SUMIFS(Transactions!$E:$E,Transactions!$C:$C,$A10,Transactions!$F:$F,"Jul") -> 0 | I10: =SUMIFS(Transactions!$E:$E,Transactions!$C:$C,$A10,Transactions!$F:$F,"Aug") -> 0 | J10: =SUMIFS(Transactions!$E:$E,Transactions!$C:$C,$A10,Transactions!$F:$F,"Sep") -> 0 | K10: =SUMIFS(Transactions!$E:$E,Transactions!$C:$C,$A10,Transactions!$F:$F,"Oct") -> 0 | L10: =SUMIFS(Transactions!$E:$E,Transactions!$C:$C,$A10,Transactions!$F:$F,"Nov") -> 0 | M10: =SUMIFS(Transactions!$E:$E,Transactions!$C:$C,$A10,Transactions!$F:$F,"Dec") -> 0 | N10: =SUM(B10:M10) -> 12880.82
A11: Partner Income | B11: =SUMIFS(Transactions!$E:$E,Transactions!$C:$C,$A11,Transactions!$F:$F,"Jan") -> 1103.53 | C11: =SUMIFS(Transactions!$E:$E,Transactions!$C:$C,$A11,Transactions!$F:$F,"Feb") -> 3991.89 | D11: =SUMIFS(Transactions!$E:$E,Transactions!$C:$C,$A11,Transactions!$F:$F,"Mar") -> 2858.2 | E11: =SUMIFS(Transactions!$E:$E,Transactions!$C:$C,$A11,Transactions!$F:$F,"Apr") -> 0 | F11: =SUMIFS(Transactions!$E:$E,Transactions!$C:$C,$A11,Transactions!$F:$F,"May") -> 0 | G11: =SUMIFS(Transactions!$E:$E,Transactions!$C:$C,$A11,Transactions!$F:$F,"Jun") -> 0 | H11: =SUMIFS(Transactions!$E:$E,Transactions!$C:$C,$A11,Transactions!$F:$F,"Jul") -> 0 | I11: =SUMIFS(Transactions!$E:$E,Transactions!$C:$C,$A11,Transactions!$F:$F,"Aug") -> 0 | J11: =SUMIFS(Transactions!$E:$E,Transactions!$C:$C,$A11,Transactions!$F:$F,"Sep") -> 0 | K11: =SUMIFS(Transactions!$E:$E,Transactions!$C:$C,$A11,Transactions!$F:$F,"Oct") -> 0 | L11: =SUMIFS(Transactions!$E:$E,Transactions!$C:$C,$A11,Transactions!$F:$F,"Nov") -> 0 | M11: =SUMIFS(Transactions!$E:$E,Transactions!$C:$C,$A11,Transactions!$F:$F,"Dec") -> 0 | N11: =SUM(B11:M11) -> 7953.62
A12: TOTAL INCOME 2 | B12: =SUM(B10:B11) -> 3358.34 | C12: =SUM(C10:C11) -> 9445.86 | D12: =SUM(D10:D11) -> 8030.24 | E12: =SUM(E10:E11) -> 0 | F12: =SUM(F10:F11) -> 0 | G12: =SUM(G10:G11) -> 0 | H12: =SUM(H10:H11) -> 0 | I12: =SUM(I10:I11) -> 0 | ... M12: =SUM(M10:M11) -> 0 | N12: =SUM(B12:M12) -> 20834.44
A13: TOTAL INCOME | B13: =SUM(B3:B12) -> 34004.1 | C13: =SUM(C3:C12) -> 44331.32 | D13: =SUM(D3:D12) -> 62483.84 | E13: =SUM(E3:E12) -> 0 | F13: =SUM(F3:F12) -> 0 | G13: =SUM(G3:G12) -> 0 | H13: =SUM(H3:H12) -> 0 | I13: =SUM(I3:I12) -> 0 | ... M13: =SUM(M3:M12) -> 0 | N13: =SUM(B13:M13) -> 140819.26
A15: EXPENSES
A16: Living Expenses | B16: =SUMIFS(Transactions!$E:$E,Transactions!$C:$C,$A16,Transactions!$F:$F,"Jan") -> -1701.49 | C16: =SUMIFS(Transactions!$E:$E,Transactions!$C:$C,$A16,Transactions!$F:$F,"Feb") -> -407.84 | D16: =SUMIFS(Transactions!$E:$E,Transactions!$C:$C,$A16,Transactions!$F:$F,"Mar") -> 0 | E16: =SUMIFS(Transactions!$E:$E,Transactions!$C:$C,$A16,Transactions!$F:$F,"Apr") -> 0 | F16: =SUMIFS(Transactions!$E:$E,Transactions!$C:$C,$A16,Transactions!$F:$F,"May") -> 0 | G16: =SUMIFS(Transactions!$E:$E,Transactions!$C:$C,$A16,Transactions!$F:$F,"Jun") -> 0 | H16: =SUMIFS(Transactions!$E:$E,Transactions!$C:$C,$A16,Transactions!$F:$F,"Jul") -> 0 | I16: =SUMIFS(Transactions!$E:$E,Transactions!$C:$C,$A16,Transactions!$F:$F,"Aug") -> 0 | J16: =SUMIFS(Transactions!$E:$E,Transactions!$C:$C,$A16,Transactions!$F:$F,"Sep") -> 0 | K16: =SUMIFS(Transactions!$E:$E,Transactions!$C:$C,$A16,Transactions!$F:$F,"Oct") -> 0 | L16: =SUMIFS(Transactions!$E:$E,Transactions!$C:$C,$A16,Transactions!$F:$F,"Nov") -> 0 | M16: =SUMIFS(Transactions!$E:$E,Transactions!$C:$C,$A16,Transactions!$F:$F,"Dec") -> 0 | N16: =SUM(B16:M16) -> -2109.33
A17: Bills | B17: =SUMIFS(Transactions!$E:$E,Transactions!$C:$C,$A17,Transactions!$F:$F,"Jan") -> -949.76 | C17: =SUMIFS(Transactions!$E:$E,Transactions!$C:$C,$A17,Transactions!$F:$F,"Feb") -> -4146.12 | D17: =SUMIFS(Transactions!$E:$E,Transactions!$C:$C,$A17,Transactions!$F:$F,"Mar") -> 0 | E17: =SUMIFS(Transactions!$E:$E,Transactions!$C:$C,$A17,Transactions!$F:$F,"Apr") -> 0 | F17: =SUMIFS(Transactions!$E:$E,Transactions!$C:$C,$A17,Transactions!$F:$F,"May") -> 0 | G17: =SUMIFS(Transactions!$E:$E,Transactions!$C:$C,$A17,Transactions!$F:$F,"Jun") -> 0 | H17: =SUMIFS(Transactions!$E:$E,Transactions!$C:$C,$A17,Transactions!$F:$F,"Jul") -> 0 | I17: =SUMIFS(Transactions!$E:$E,Transactions!$C:$C,$A17,Transactions!$F:$F,"Aug") -> 0 | J17: =SUMIFS(Transactions!$E:$E,Transactions!$C:$C,$A17,Transactions!$F:$F,"Sep") -> 0 | K17: =SUMIFS(Transactions!$E:$E,Transactions!$C:$C,$A17,Transactions!$F:$F,"Oct") -> 0 | L17: =SUMIFS(Transactions!$E:$E,Transactions!$C:$C,$A17,Transactions!$F:$F,"Nov") -> 0 | M17: =SUMIFS(Transactions!$E:$E,Transactions!$C:$C,$A17,Transactions!$F:$F,"Dec") -> 0 | N17: =SUM(B17:M17) -> -5095.88
A18: Housing | B18: =SUMIFS(Transactions!$E:$E,Transactions!$C:$C,$A18,Transactions!$F:$F,"Jan") -> -1007.31 | C18: =SUMIFS(Transactions!$E:$E,Transactions!$C:$C,$A18,Transactions!$F:$F,"Feb") -> -1221.83 | D18: =SUMIFS(Transactions!$E:$E,Transactions!$C:$C,$A18,Transactions!$F:$F,"Mar") -> -1570.03 | E18: =SUMIFS(Transactions!$E:$E,Transactions!$C:$C,$A18,Transactions!$F:$F,"Apr") -> 0 | F18: =SUMIFS(Transactions!$E:$E,Transactions!$C:$C,$A18,Transactions!$F:$F,"May") -> 0 | G18: =SUMIFS(Transactions!$E:$E,Transactions!$C:$C,$A18,Transactions!$F:$F,"Jun") -> 0 | H18: =SUMIFS(Transactions!$E:$E,Transactions!$C:$C,$A18,Transactions!$F:$F,"Jul") -> 0 | I18: =SUMIFS(Transactions!$E:$E,Transactions!$C:$C,$A18,Transactions!$F:$F,"Aug") -> 0 | J18: =SUMIFS(Transactions!$E:$E,Transactions!$C:$C,$A18,Transactions!$F:$F,"Sep") -> 0 | K18: =SUMIFS(Transactions!$E:$E,Transactions!$C:$C,$A18,Transactions!$F:$F,"Oct") -> 0 | L18: =SUMIFS(Transactions!$E:$E,Transactions!$C:$C,$A18,Transactions!$F:$F,"Nov") -> 0 | M18: =SUMIFS(Transactions!$E:$E,Transactions!$C:$C,$A18,Transactions!$F:$F,"Dec") -> 0 | N18: =SUM(B18:M18) -> -3799.17
A19: Transport | B19: =SUMIFS(Transactions!$E:$E,Transactions!$C:$C,$A19,Transactions!$F:$F,"Jan") -> -312.45 | C19: =SUMIFS(Transactions!$E:$E,Transactions!$C:$C,$A19,Transactions!$F:$F,"Feb") -> -2243.66 | D19: =SUMIFS(Transactions!$E:$E,Transactions!$C:$C,$A19,Transactions!$F:$F,"Mar") -> -1212.98 | E19: =SUMIFS(Transactions!$E:$E,Transactions!$C:$C,$A19,Transactions!$F:$F,"Apr") -> 0 | F19: =SUMIFS(Transactions!$E:$E,Transactions!$C:$C,$A19,Transactions!$F:$F,"May") -> 0 | G19: =SUMIFS(Transactions!$E:$E,Transactions!$C:$C,$A19,Transactions!$F:$F,"Jun") -> 0 | H19: =SUMIFS(Transactions!$E:$E,Transactions!$C:$C,$A19,Transactions!$F:$F,"Jul") -> 0 | I19: =SUMIFS(Transactions!$E:$E,Transactions!$C:$C,$A19,Transactions!$F:$F,"Aug") -> 0 | J19: =SUMIFS(Transactions!$E:$E,Transactions!$C:$C,$A19,Transactions!$F:$F,"Sep") -> 0 | K19: =SUMIFS(Transactions!$E:$E,Transactions!$C:$C,$A19,Transactions!$F:$F,"Oct") -> 0 | L19: =SUMIFS(Transactions!$E:$E,Transactions!$C:$C,$A19,Transactions!$F:$F,"Nov") -> 0 | M19: =SUMIFS(Transactions!$E:$E,Transactions!$C:$C,$A19,Transactions!$F:$F,"Dec") -> 0 | N19: =SUM(B19:M19) -> -3769.09
A20: Discretionary Spending | B20: =SUMIFS(Transactions!$E:$E,Transactions!$C:$C,$A20,Transactions!$F:$F,"Jan") -> -3910.42 | C20: =SUMIFS(Transactions!$E:$E,Transactions!$C:$C,$A20,Transactions!$F:$F,"Feb") -> -1433.71 | D20: =SUMIFS(Transactions!$E:$E,Transactions!$C:$C,$A20,Transactions!$F:$F,"Mar") -> -3410.41 | E20: =SUMIFS(Transactions!$E:$E,Transactions!$C:$C,$A20,Transactions!$F:$F,"Apr") -> 0 | F20: =SUMIFS(Transactions!$E:$E,Transactions!$C:$C,$A20,Transactions!$F:$F,"May") -> 0 | G20: =SUMIFS(Transactions!$E:$E,Transactions!$C:$C,$A20,Transactions!$F:$F,"Jun") -> 0 | H20: =SUMIFS(Transactions!$E:$E,Transactions!$C:$C,$A20,Transactions!$F:$F,"Jul") -> 0 | I20: =SUMIFS(Transactions!$E:$E,Transactions!$C:$C,$A20,Transactions!$F:$F,"Aug") -> 0 | J20: =SUMIFS(Transactions!$E:$E,Transactions!$C:$C,$A20,Transactions!$F:$F,"Sep") -> 0 | K20: =SUMIFS(Transactions!$E:$E,Transactions!$C:$C,$A20,Transactions!$F:$F,"Oct") -> 0 | L20: =SUMIFS(Transactions!$E:$E,Transactions!$C:$C,$A20,Transactions!$F:$F,"Nov") -> 0 | M20: =SUMIFS(Transactions!$E:$E,Transactions!$C:$C,$A20,Transactions!$F:$F,"Dec") -> 0 | N20: =SUM(B20:M20) -> -8754.54
A21: Insurance | B21: =SUMIFS(Transactions!$E:$E,Transactions!$C:$C,$A21,Transactions!$F:$F,"Jan") -> -2076.64 | C21: =SUMIFS(Transactions!$E:$E,Transactions!$C:$C,$A21,Transactions!$F:$F,"Feb") -> -3750.35 | D21: =SUMIFS(Transactions!$E:$E,Transactions!$C:$C,$A21,Transactions!$F:$F,"Mar") -> -802.16 | E21: =SUMIFS(Transactions!$E:$E,Transactions!$C:$C,$A21,Transactions!$F:$F,"Apr") -> 0 | F21: =SUMIFS(Transactions!$E:$E,Transactions!$C:$C,$A21,Transactions!$F:$F,"May") -> 0 | G21: =SUMIFS(Transactions!$E:$E,Transactions!$C:$C,$A21,Transactions!$F:$F,"Jun") -> 0 | H21: =SUMIFS(Transactions!$E:$E,Transactions!$C:$C,$A21,Transactions!$F:$F,"Jul") -> 0 | I21: =SUMIFS(Transactions!$E:$E,Transactions!$C:$C,$A21,Transactions!$F:$F,"Aug") -> 0 | J21: =SUMIFS(Transactions!$E:$E,Transactions!$C:$C,$A21,Transactions!$F:$F,"Sep") -> 0 | K21: =SUMIFS(Transactions!$E:$E,Transactions!$C:$C,$A21,Transactions!$F:$F,"Oct") -> 0 | L21: =SUMIFS(Transactions!$E:$E,Transactions!$C:$C,$A21,Transactions!$F:$F,"Nov") -> 0 | M21: =SUMIFS(Transactions!$E:$E,Transactions!$C:$C,$A21,Transactions!$F:$F,"Dec") -> 0 | N21: =SUM(B21:M21) -> -6629.15
A22: Health | B22: =SUMIFS(Transactions!$E:$E,Transactions!$C:$C,$A22,Transactions!$F:$F,"Jan") -> -2508.4 | C22: =SUMIFS(Transactions!$E:$E,Transactions!$C:$C,$A22,Transactions!$F:$F,"Feb") -> -149.01 | D22: =SUMIFS(Transactions!$E:$E,Transactions!$C:$C,$A22,Transactions!$F:$F,"Mar") -> -3300.72 | E22: =SUMIFS(Transactions!$E:$E,Transactions!$C:$C,$A22,Transactions!$F:$F,"Apr") -> 0 | F22: =SUMIFS(Transactions!$E:$E,Transactions!$C:$C,$A22,Transactions!$F:$F,"May") -> 0 | G22: =SUMIFS(Transactions!$E:$E,Transactions!$C:$C,$A22,Transactions!$F:$F,"Jun") -> 0 | H22: =SUMIFS(Transactions!$E:$E,Transactions!$C:$C,$A22,Transactions!$F:$F,"Jul") -> 0 | I22: =SUMIFS(Transactions!$E:$E,Transactions!$C:$C,$A22,Transactions!$F:$F,"Aug") -> 0 | J22: =SUMIFS(Transactions!$E:$E,Transactions!$C:$C,$A22,Transactions!$F:$F,"Sep") -> 0 | K22: =SUMIFS(Transactions!$E:$E,Transactions!$C:$C,$A22,Transactions!$F:$F,"Oct") -> 0 | L22: =SUMIFS(Transactions!$E:$E,Transactions!$C:$C,$A22,Transactions!$F:$F,"Nov") -> 0 | M22: =SUMIFS(Transactions!$E:$E,Transactions!$C:$C,$A22,Transactions!$F:$F,"Dec") -> 0 | N22: =SUM(B22:M22) -> -5958.13
A23: Groceries | B23: =SUMIFS(Transactions!$E:$E,Transactions!$C:$C,$A23,Transactions!$F:$F,"Jan") -> -1437.93 | C23: =SUMIFS(Transactions!$E:$E,Transactions!$C:$C,$A23,Transactions!$F:$F,"Feb") -> -3734.66 | D23: =SUMIFS(Transactions!$E:$E,Transactions!$C:$C,$A23,Transactions!$F:$F,"Mar") -> -1695.54 | E23: =SUMIFS(Transactions!$E:$E,Transactions!$C:$C,$A23,Transactions!$F:$F,"Apr") -> 0 | F23: =SUMIFS(Transactions!$E:$E,Transactions!$C:$C,$A23,Transactions!$F:$F,"May") -> 0 | G23: =SUMIFS(Transactions!$E:$E,Transactions!$C:$C,$A23,Transactions!$F:$F,"Jun") -> 0 | H23: =SUMIFS(Transactions!$E:$E,Transactions!$C:$C,$A23,Transactions!$F:$F,"Jul") -> 0 | I23: =SUMIFS(Transactions!$E:$E,Transactions!$C:$C,$A23,Transactions!$F:$F,"Aug") -> 0 | J23: =SUMIFS(Transactions!$E:$E,Transactions!$C:$C,$A23,Transactions!$F:$F,"Sep") -> 0 | K23: =SUMIFS(Transactions!$E:$E,Transactions!$C:$C,$A23,Transactions!$F:$F,"Oct") -> 0 | L23: =SUMIFS(Transactions!$E:$E,Transactions!$C:$C,$A23,Transactions!$F:$F,"Nov") -> 0 | M23: =SUMIFS(Transactions!$E:$E,Transactions!$C:$C,$A23,Transactions!$F:$F,"Dec") -> 0 | N23: =SUM(B23:M23) -> -6868.13
A24: Dining | B24: =SUMIFS(Transactions!$E:$E,Transactions!$C:$C,$A24,Transactions!$F:$F,"Jan") -> -1906.45 | C24: =SUMIFS(Transactions!$E:$E,Transactions!$C:$C,$A24,Transactions!$F:$F,"Feb") -> -2561.1 | D24: =SUMIFS(Transactions!$E:$E,Transactions!$C:$C,$A24,Transactions!$F:$F,"Mar") -> -3069.48 | E24: =SUMIFS(Transactions!$E:$E,Transactions!$C:$C,$A24,Transactions!$F:$F,"Apr") -> 0 | F24: =SUMIFS(Transactions!$E:$E,Transactions!$C:$C,$A24,Transactions!$F:$F,"May") -> 0 | G24: =SUMIFS(Transactions!$E:$E,Transactions!$C:$C,$A24,Transactions!$F:$F,"Jun") -> 0 | H24: =SUMIFS(Transactions!$E:$E,Transactions!$C:$C,$A24,Transactions!$F:$F,"Jul") -> 0 | I24: =SUMIFS(Transactions!$E:$E,Transactions!$C:$C,$A24,Transactions!$F:$F,"Aug") -> 0 | J24: =SUMIFS(Transactions!$E:$E,Transactions!$C:$C,$A24,Transactions!$F:$F,"Sep") -> 0 | K24: =SUMIFS(Transactions!$E:$E,Transactions!$C:$C,$A24,Transactions!$F:$F,"Oct") -> 0 | L24: =SUMIFS(Transactions!$E:$E,Transactions!$C:$C,$A24,Transactions!$F:$F,"Nov") -> 0 | M24: =SUMIFS(Transactions!$E:$E,Transactions!$C:$C,$A24,Transactions!$F:$F,"Dec") -> 0 | N24: =SUM(B24:M24) -> -7537.03
A25: Travel | B25: =SUMIFS(Transactions!$E:$E,Transactions!$C:$C,$A25,Transactions!$F:$F,"Jan") -> -729.89 | C25: =SUMIFS(Transactions!$E:$E,Transactions!$C:$C,$A25,Transactions!$F:$F,"Feb") -> -2619.46 | D25: =SUMIFS(Transactions!$E:$E,Transactions!$C:$C,$A25,Transactions!$F:$F,"Mar") -> -6658.91 | E25: =SUMIFS(Transactions!$E:$E,Transactions!$C:$C,$A25,Transactions!$F:$F,"Apr") -> 0 | F25: =SUMIFS(Transactions!$E:$E,Transactions!$C:$C,$A25,Transactions!$F:$F,"May") -> 0 | G25: =SUMIFS(Transactions!$E:$E,Transactions!$C:$C,$A25,Transactions!$F:$F,"Jun") -> 0 | H25: =SUMIFS(Transactions!$E:$E,Transactions!$C:$C,$A25,Transactions!$F:$F,"Jul") -> 0 | I25: =SUMIFS(Transactions!$E:$E,Transactions!$C:$C,$A25,Transactions!$F:$F,"Aug") -> 0 | J25: =SUMIFS(Transactions!$E:$E,Transactions!$C:$C,$A25,Transactions!$F:$F,"Sep") -> 0 | K25: =SUMIFS(Transactions!$E:$E,Transactions!$C:$C,$A25,Transactions!$F:$F,"Oct") -> 0 | L25: =SUMIFS(Transactions!$E:$E,Transactions!$C:$C,$A25,Transactions!$F:$F,"Nov") -> 0 | M25: =SUMIFS(Transactions!$E:$E,Transactions!$C:$C,$A25,Transactions!$F:$F,"Dec") -> 0 | N25: =SUM(B25:M25) -> -10008.26
A26: TOTAL EXPENSES | B26: =SUM(B16:B25) -> -16540.74 | C26: =SUM(C16:C25) -> -22267.74 | D26: =SUM(D16:D25) -> -21720.23 | E26: =SUM(E16:E25) -> 0 | F26: =SUM(F16:F25) -> 0 | G26: =SUM(G16:G25) -> 0 | H26: =SUM(H16:H25) -> 0 | I26: =SUM(I16:I25) -> 0 | ... M26: =SUM(M16:M25) -> 0 | N26: =SUM(B26:M26) -> -60528.71

Sheet Categories
A1: Category | B1: Type | C1: Default Monthly Budget
A2: Main Income Source | B2: Income | C2: 3000
A3: Interest - Bank Accounts | B3: Income | C3: 10
A4: Share Dividends | B4: Income | C4: 50
A5: eBay | B5: Income | C5: 0
A6: Side Hustle | B6: Income | C6: 1200
A7: Partner Income | B7: Income | C7: 2000
A8: Savings | B8: Savings | C8: 500
A9: Living Expenses | B9: Expense | C9: 200
A10: Bills | B10: Expense | C10: 400
A11: Housing | B11: Expense | C11: 1500
A12: Transport | B12: Expense | C12: 250
A13: Discretionary Spending | B13: Expense | C13: 350
... A18: Travel | B18: Expense | C18: 300

Sheet Income-Expense By Month
A1: Month | B1: Income | C1: Expenses | D1: Net | E1: Savings | F1: Savings Rate
A2: Jan | B2: =SUMIFS(#REF!,#REF!,$A2,#REF!,"Income") -> #REF! | C2: =SUMIFS(#REF!,#REF!,$A2,#REF!,"Expense") -> #REF! | D2: =B2-C2 -> #REF! | E2: =SUMIFS(#REF!,#REF!,$A2,#REF!,"Savings") -> #REF! | F2: =IF(B2=0,0,E2/B2) -> #REF!
A3: Feb | B3: =SUMIFS(#REF!,#REF!,$A3,#REF!,"Income") -> #REF! | C3: =SUMIFS(#REF!,#REF!,$A3,#REF!,"Expense") -> #REF! | D3: =B3-C3 -> #REF! | E3: =SUMIFS(#REF!,#REF!,$A3,#REF!,"Savings") -> #REF! | F3: =IF(B3=0,0,E3/B3) -> #REF!
A4: Mar | B4: =SUMIFS(#REF!,#REF!,$A4,#REF!,"Income") -> #REF! | C4: =SUMIFS(#REF!,#REF!,$A4,#REF!,"Expense") -> #REF! | D4: =B4-C4 -> #REF! | E4: =SUMIFS(#REF!,#REF!,$A4,#REF!,"Savings") -> #REF! | F4: =IF(B4=0,0,E4/B4) -> #REF!
A5: Apr | B5: =SUMIFS(#REF!,#REF!,$A5,#REF!,"Income") -> #REF! | C5: =SUMIFS(#REF!,#REF!,$A5,#REF!,"Expense") -> #REF! | D5: =B5-C5 -> #REF! | E5: =SUMIFS(#REF!,#REF!,$A5,#REF!,"Savings") -> #REF! | F5: =IF(B5=0,0,E5/B5) -> #REF!
A6: May | B6: =SUMIFS(#REF!,#REF!,$A6,#REF!,"Income") -> #REF! | C6: =SUMIFS(#REF!,#REF!,$A6,#REF!,"Expense") -> #REF! | D6: =B6-C6 -> #REF! | E6: =SUMIFS(#REF!,#REF!,$A6,#REF!,"Savings") -> #REF! | F6: =IF(B6=0,0,E6/B6) -> #REF!
A7: Jun | B7: =SUMIFS(#REF!,#REF!,$A7,#REF!,"Income") -> #REF! | C7: =SUMIFS(#REF!,#REF!,$A7,#REF!,"Expense") -> #REF! | D7: =B7-C7 -> #REF! | E7: =SUMIFS(#REF!,#REF!,$A7,#REF!,"Savings") -> #REF! | F7: =IF(B7=0,0,E7/B7) -> #REF!
A8: Jul | B8: =SUMIFS(#REF!,#REF!,$A8,#REF!,"Income") -> #REF! | C8: =SUMIFS(#REF!,#REF!,$A8,#REF!,"Expense") -> #REF! | D8: =B8-C8 -> #REF! | E8: =SUMIFS(#REF!,#REF!,$A8,#REF!,"Savings") -> #REF! | F8: =IF(B8=0,0,E8/B8) -> #REF!
A9: Aug | B9: =SUMIFS(#REF!,#REF!,$A9,#REF!,"Income") -> #REF! | C9: =SUMIFS(#REF!,#REF!,$A9,#REF!,"Expense") -> #REF! | D9: =B9-C9 -> #REF! | E9: =SUMIFS(#REF!,#REF!,$A9,#REF!,"Savings") -> #REF! | F9: =IF(B9=0,0,E9/B9) -> #REF!
A10: Sep | B10: =SUMIFS(#REF!,#REF!,$A10,#REF!,"Income") -> #REF! | C10: =SUMIFS(#REF!,#REF!,$A10,#REF!,"Expense") -> #REF! | D10: =B10-C10 -> #REF! | E10: =SUMIFS(#REF!,#REF!,$A10,#REF!,"Savings") -> #REF! | F10: =IF(B10=0,0,E10/B10) -> #REF!
A11: Oct | B11: =SUMIFS(#REF!,#REF!,$A11,#REF!,"Income") -> #REF! | C11: =SUMIFS(#REF!,#REF!,$A11,#REF!,"Expense") -> #REF! | D11: =B11-C11 -> #REF! | E11: =SUMIFS(#REF!,#REF!,$A11,#REF!,"Savings") -> #REF! | F11: =IF(B11=0,0,E11/B11) -> #REF!
A12: Nov | B12: =SUMIFS(#REF!,#REF!,$A12,#REF!,"Income") -> #REF! | C12: =SUMIFS(#REF!,#REF!,$A12,#REF!,"Expense") -> #REF! | D12: =B12-C12 -> #REF! | E12: =SUMIFS(#REF!,#REF!,$A12,#REF!,"Savings") -> #REF! | F12: =IF(B12=0,0,E12/B12) -> #REF!
A13: Dec | B13: =SUMIFS(#REF!,#REF!,$A13,#REF!,"Income") -> #REF! | C13: =SUMIFS(#REF!,#REF!,$A13,#REF!,"Expense") -> #REF! | D13: =B13-C13 -> #REF! | E13: =SUMIFS(#REF!,#REF!,$A13,#REF!,"Savings") -> #REF! | F13: =IF(B13=0,0,E13/B13) -> #REF!

Sheet Annual Summary
A1: Month | B1: Expected Income | C1: Expected Expenses | D1: Actual Income | E1: Actual Expenses | F1: Net | G1: Notes
A2: Jan | B2: =SUMIF(Categories!$B:$B,"Income",Categories!$C:$C) -> 6260 | C2: =SUMIF(Categories!$B:$B,"Expense",Categories!$C:$C) -> 4450 | D2: =SUMIFS(Transactions!$E:$E,Transactions!$F:$F,$A2,Transactions!$G:$G,"Income") -> 17002.05 | E2: =ABS(SUMIFS(Transactions!$E:$E,Transactions!$F:$F,$A2,Transactions!$G:$G,"Expense")) -> 16540.74 | F2: =D2-E2 -> 461.31
A3: Feb | B3: =SUMIF(Categories!$B:$B,"Income",Categories!$C:$C) -> 6260 | C3: =SUMIF(Categories!$B:$B,"Expense",Categories!$C:$C) -> 4450 | D3: =SUMIFS(Transactions!$E:$E,Transactions!$F:$F,$A3,Transactions!$G:$G,"Income") -> 22165.66 | E3: =ABS(SUMIFS(Transactions!$E:$E,Transactions!$F:$F,$A3,Transactions!$G:$G,"Expense")) -> 22267.74 | F3: =D3-E3 -> -102.08
A4: Mar | B4: =SUMIF(Categories!$B:$B,"Income",Categories!$C:$C) -> 6260 | C4: =SUMIF(Categories!$B:$B,"Expense",Categories!$C:$C) -> 4450 | D4: =SUMIFS(Transactions!$E:$E,Transactions!$F:$F,$A4,Transactions!$G:$G,"Income") -> 31241.92 | E4: =ABS(SUMIFS(Transactions!$E:$E,Transactions!$F:$F,$A4,Transactions!$G:$G,"Expense")) -> 21720.23 | F4: =D4-E4 -> 9521.69
A5: Apr | B5: =SUMIF(Categories!$B:$B,"Income",Categories!$C:$C) -> 6260 | C5: =SUMIF(Categories!$B:$B,"Expense",Categories!$C:$C) -> 4450 | D5: =SUMIFS(Transactions!$E:$E,Transactions!$F:$F,$A5,Transactions!$G:$G,"Income") -> 0 | E5: =ABS(SUMIFS(Transactions!$E:$E,Transactions!$F:$F,$A5,Transactions!$G:$G,"Expense")) -> 0 | F5: =D5-E5 -> 0
A6: May | B6: =SUMIF(Categories!$B:$B,"Income",Categories!$C:$C) -> 6260 | C6: =SUMIF(Categories!$B:$B,"Expense",Categories!$C:$C) -> 4450 | D6: =SUMIFS(Transactions!$E:$E,Transactions!$F:$F,$A6,Transactions!$G:$G,"Income") -> 0 | E6: =ABS(SUMIFS(Transactions!$E:$E,Transactions!$F:$F,$A6,Transactions!$G:$G,"Expense")) -> 0 | F6: =D6-E6 -> 0
A7: Jun | B7: =SUMIF(Categories!$B:$B,"Income",Categories!$C:$C) -> 6260 | C7: =SUMIF(Categories!$B:$B,"Expense",Categories!$C:$C) -> 4450 | D7: =SUMIFS(Transactions!$E:$E,Transactions!$F:$F,$A7,Transactions!$G:$G,"Income") -> 0 | E7: =ABS(SUMIFS(Transactions!$E:$E,Transactions!$F:$F,$A7,Transactions!$G:$G,"Expense")) -> 0 | F7: =D7-E7 -> 0
A8: Jul | B8: =SUMIF(Categories!$B:$B,"Income",Categories!$C:$C) -> 6260 | C8: =SUMIF(Categories!$B:$B,"Expense",Categories!$C:$C) -> 4450 | D8: =SUMIFS(Transactions!$E:$E,Transactions!$F:$F,$A8,Transactions!$G:$G,"Income") -> 0 | E8: =ABS(SUMIFS(Transactions!$E:$E,Transactions!$F:$F,$A8,Transactions!$G:$G,"Expense")) -> 0 | F8: =D8-E8 -> 0
A9: Aug | B9: =SUMIF(Categories!$B:$B,"Income",Categories!$C:$C) -> 6260 | C9: =SUMIF(Categories!$B:$B,"Expense",Categories!$C:$C) -> 4450 | D9: =SUMIFS(Transactions!$E:$E,Transactions!$F:$F,$A9,Transactions!$G:$G,"Income") -> 0 | E9: =ABS(SUMIFS(Transactions!$E:$E,Transactions!$F:$F,$A9,Transactions!$G:$G,"Expense")) -> 0 | F9: =D9-E9 -> 0
A10: Sep | B10: =SUMIF(Categories!$B:$B,"Income",Categories!$C:$C) -> 6260 | C10: =SUMIF(Categories!$B:$B,"Expense",Categories!$C:$C) -> 4450 | D10: =SUMIFS(Transactions!$E:$E,Transactions!$F:$F,$A10,Transactions!$G:$G,"Income") -> 0 | E10: =ABS(SUMIFS(Transactions!$E:$E,Transactions!$F:$F,$A10,Transactions!$G:$G,"Expense")) -> 0 | F10: =D10-E10 -> 0
A11: Oct | B11: =SUMIF(Categories!$B:$B,"Income",Categories!$C:$C) -> 6260 | C11: =SUMIF(Categories!$B:$B,"Expense",Categories!$C:$C) -> 4450 | D11: =SUMIFS(Transactions!$E:$E,Transactions!$F:$F,$A11,Transactions!$G:$G,"Income") -> 0 | E11: =ABS(SUMIFS(Transactions!$E:$E,Transactions!$F:$F,$A11,Transactions!$G:$G,"Expense")) -> 0 | F11: =D11-E11 -> 0
A12: Nov | B12: =SUMIF(Categories!$B:$B,"Income",Categories!$C:$C) -> 6260 | C12: =SUMIF(Categories!$B:$B,"Expense",Categories!$C:$C) -> 4450 | D12: =SUMIFS(Transactions!$E:$E,Transactions!$F:$F,$A12,Transactions!$G:$G,"Income") -> 0 | E12: =ABS(SUMIFS(Transactions!$E:$E,Transactions!$F:$F,$A12,Transactions!$G:$G,"Expense")) -> 0 | F12: =D12-E12 -> 0
A13: Dec | B13: =SUMIF(Categories!$B:$B,"Income",Categories!$C:$C) -> 6260 | C13: =SUMIF(Categories!$B:$B,"Expense",Categories!$C:$C) -> 4450 | D13: =SUMIFS(Transactions!$E:$E,Transactions!$F:$F,$A13,Transactions!$G:$G,"Income") -> 0 | E13: =ABS(SUMIFS(Transactions!$E:$E,Transactions!$F:$F,$A13,Transactions!$G:$G,"Expense")) -> 0 | F13: =D13-E13 -> 0

Sheet Savings Tracker
A1: Month | B1: Target Savings | C1: Actual Savings | D1: Variance
A2: Jan | C2: ='Income-Expense By Month'!E2 -> #REF! | D2: =C2-B2 -> #REF!
A3: Feb | C3: ='Income-Expense By Month'!E3 -> #REF! | D3: =C3-B3 -> #REF!
A4: Mar | C4: ='Income-Expense By Month'!E4 -> #REF! | D4: =C4-B4 -> #REF!
A5: Apr | C5: ='Income-Expense By Month'!E5 -> #REF! | D5: =C5-B5 -> #REF!
A6: May | C6: ='Income-Expense By Month'!E6 -> #REF! | D6: =C6-B6 -> #REF!
A7: Jun | C7: ='Income-Expense By Month'!E7 -> #REF! | D7: =C7-B7 -> #REF!
A8: Jul | C8: ='Income-Expense By Month'!E8 -> #REF! | D8: =C8-B8 -> #REF!
A9: Aug | C9: ='Income-Expense By Month'!E9 -> #REF! | D9: =C9-B9 -> #REF!
A10: Sep | C10: ='Income-Expense By Month'!E10 -> #REF! | D10: =C10-B10 -> #REF!
A11: Oct | C11: ='Income-Expense By Month'!E11 -> #REF! | D11: =C11-B11 -> #REF!
A12: Nov | C12: ='Income-Expense By Month'!E12 -> #REF! | D12: =C12-B12 -> #REF!
A13: Dec | C13: ='Income-Expense By Month'!E13 -> #REF! | D13: =C13-B13 -> #REF!

Sheet Tax Deductions
A1: Deduction Category | B1: Amount | C1: Notes
A2: Home Office
A3: Business Travel
A4: Meals & Entertainment
A5: Vehicle Mileage
A6: Supplies & Equipment
A7: Health Insurance Premiums
A8: Retirement Contributions
A9: Education & Training
A10: Charitable Donations
A11: Property Taxes

Sheet Charts

Sheet Settings & Help
A1: Brand Primary Color | B1: #1B5E20
A2: Brand Secondary Color | B2: #FFD54F
A4: Instructions
A5: 1. Enter transactions on the 'Transactions' sheet. 2. Use the dropdown in 'Category' to classify each entry (expand the list in 'Categories' if needed). 3. Monthly and Annual summaries update automatically. 4. Adjust target savings in 'Savings Tracker'. 5. Log deductible expenses in 'Tax Deductions'. 6. Dashboard & Charts reflect your data automatically. 7. Future versions will add CSV import & macro buttons for refresh, plus sheet protection.
